{
  "schema_version": "2.0.0",
  "setup_id": "RGNT_20260703_001",
  "symbol": "RGNT",
  "enabled": true,
  "mode": "paper",
  "setup_type": "range_breakout",
  "setup_role": "ENTRY_AND_MANAGEMENT",
  "direction": "long",
  "timeframes": {
    "signal": "15m",
    "confirmation": "1d",
    "trailing_management": "15m",
    "atr_reference": "1h"
  },
  "range": {
    "high": 4.55,
    "low": 3.5,
    "breakout_side": "up",
    "require_close_outside_range": true
  },
  "entry": {
    "enabled": true,
    "order_type": "STP_LMT",
    "trigger_offset": 0.02,
    "limit_offset": 0.05,
    "trigger_price": 4.57,
    "entry_price": 4.57,
    "limit_price": 4.62,
    "maximum_limit_price": 4.62,
    "cancel_if_not_filled_after_minutes": 30,
    "requires_trailing_stop_before_transmission": true
  },
  "risk": {
    "max_position_amount_usd": 250,
    "max_risk_usd": 15,
    "risk_model": "TRAILING_STOP_INITIAL_RISK",
    "maximum_quantity": 26,
    "planned_position_amount_usd": 120.12,
    "planned_risk_per_share_usd": 0.56,
    "planned_max_risk_usd": 14.56,
    "emergency_exit_if_stop_fails": true,
    "block_entry_if_risk_unknown": true,
    "block_entry_if_trailing_stop_missing": true
  },
  "trailing_stop_loss": {
    "enabled": true,
    "mode": "AUTO_INTELLIGENT",
    "initial_stop": 4.06,
    "current_stop": null,
    "never_lower_stop": true,
    "stop_source": "STRUCTURE_BASED",
    "applies_to": "ENTRY_AND_POSITION_MANAGEMENT",
    "migration_status": "MIGRATED_TO_TRAILING_STOP",
    "activation": {
      "mode": "ON_ENTRY_FILL",
      "activate_before_entry_transmission": true,
      "entry_order_requires_attached_trailing_stop": true
    },
    "calculation": {
      "method": "HYBRID_ATR_STRUCTURE",
      "allowed_methods": [
        "ATR_BASED",
        "STRUCTURE_BASED",
        "HYBRID_ATR_STRUCTURE",
        "PERCENT_BASED_FALLBACK"
      ],
      "default_method": "HYBRID_ATR_STRUCTURE",
      "atr": {
        "timeframe": "1h",
        "period": 14,
        "multiplier_initial": 1.5,
        "multiplier_trailing": 1.5,
        "min_multiplier": 1,
        "max_multiplier": 3.5
      },
      "structure": {
        "reference": "BROKEN_RESISTANCE_AS_SUPPORT",
        "allowed_references": [
          "HIGHER_LOW",
          "INTRADAY_SUPPORT",
          "RANGE_LOW",
          "BROKEN_RESISTANCE_AS_SUPPORT",
          "VWAP_PULLBACK",
          "PREVIOUS_DAY_LOW",
          "AUTO_SELECT"
        ],
        "buffer_policy": "MAX_OF_TICK_SPREAD_ATR_FRACTION",
        "min_tick_buffer": 2,
        "spread_buffer_multiplier": 2,
        "atr_fraction_buffer": 0.1
      },
      "stock_specific_adjustment": {
        "enabled": true,
        "inputs": [
          "price",
          "atr_15m",
          "atr_1h",
          "average_true_range_percent",
          "spread_bps",
          "relative_volume",
          "liquidity",
          "gap_percent",
          "intraday_range_percent",
          "sector_volatility",
          "distance_to_support",
          "distance_to_breakout_level"
        ],
        "volatility_regime": "AUTO",
        "liquidity_regime": "AUTO",
        "spread_regime": "AUTO"
      },
      "risk_constraints": {
        "respect_max_risk_usd": true,
        "respect_max_position_amount_usd": true,
        "minimum_quantity": 1,
        "block_if_quantity_zero": true,
        "block_if_initial_stop_above_entry_for_long": true,
        "block_if_initial_stop_below_entry_for_short": true
      }
    },
    "ratchet_rules": {
      "enabled": true,
      "move_only_up_for_long": true,
      "move_only_down_for_short": true,
      "update_on_closed_bar_only": true,
      "timeframe": "15m",
      "min_improvement_required": "AUTO",
      "min_improvement_atr_fraction": 0.15,
      "do_not_lower_stop": true,
      "do_not_update_outside_rth": true,
      "do_not_update_if_spread_wide": true,
      "do_not_update_on_unconfirmed_intrabar_move": true,
      "allow_break_even_move": true,
      "break_even_policy": {
        "enabled": true,
        "trigger_after_profit_r_multiple": 1,
        "new_stop": "ENTRY_PRICE_PLUS_FEES_BUFFER"
      }
    },
    "broker_order": {
      "order_type": "TRAIL_OR_MANAGED_STOP",
      "attach_to_entry_order": true,
      "required_before_entry_transmission": true,
      "use_native_ibkr_trailing_order_if_available": true,
      "fallback_to_managed_stop_updates": true,
      "parent_child_bracket_required": true,
      "entry_parent_transmit": false,
      "trailing_stop_child_transmit": true,
      "block_if_broker_stop_not_confirmed": true,
      "trailing_stop_order_ready": false
    },
    "audit": {
      "record_initial_stop_calculation": true,
      "record_each_stop_update": true,
      "record_reason": true,
      "record_old_stop": true,
      "record_new_stop": true,
      "record_broker_order_id": true
    }
  },
  "management": {
    "take_profit_mode": "none",
    "never_lower_stop": true,
    "position_management_mode": "TRAILING_STOP_ONLY",
    "stop_management": {
      "mode": "TRAILING_STOP_LOSS",
      "source": "trailing_stop_loss",
      "never_lower_stop": true,
      "steps": [],
      "trail_type": "ATR_OR_STRUCTURE",
      "atr_timeframe": "1h",
      "atr_multiplier": 1.5
    }
  },
  "volume_confirmation": {
    "enabled": true,
    "signal_timeframe": "15m",
    "comparison_mode": "SAME_TIME_OF_DAY",
    "average_sample_days": 20,
    "fast_volume_ratio_min": 1.5,
    "normal_volume_ratio_min": 1,
    "confirmed_volume_ratio_min": 0.8,
    "confirmed_hold_bars": 2,
    "close_above_level_required": true,
    "reject_detection_enabled": true,
    "max_upper_wick_ratio": 0.5
  },
  "missed_breakout": {
    "retest_zone_min": 4.42,
    "retest_zone_max": 4.55
  },
  "rearm": {
    "new_local_resistance": 4.85,
    "new_trigger": 4.87,
    "new_limit": 4.92
  },
  "anti_chase": {
    "enabled": true,
    "max_price_above_entry_percent": 1.5,
    "action_if_too_far": "MISSED_BREAKOUT_WAIT_RETEST",
    "block_entry_if_price_above_maximum_limit": true
  },
  "session_policy": {
    "enabled": true,
    "require_regular_trading_hours_for_entry": true,
    "allow_premarket_entry": false,
    "allow_after_hours_entry": false,
    "wait_after_open_minutes": 30,
    "wait_closed_bars_after_open": 2,
    "wait_bars_timeframe": "15m",
    "require_rth_volume_confirmation": true,
    "require_rth_spread_check": true,
    "require_rth_risk_recalculation": true,
    "extended_hours": {
      "allow_detection": true,
      "allow_auto_execution": false,
      "allow_manual_review": true
    }
  },
  "broker_safety": {
    "require_broker_tracker": true,
    "block_if_broker_tracker_stale": true,
    "block_if_tws_disconnected": true,
    "block_if_position_without_stop": true,
    "block_if_entry_order_without_trailing_stop": true,
    "block_if_reconciliation_mismatch": true
  },
  "entry_decision": {
    "status": "WAITING_TRIGGER",
    "decision": "NO_ENTRY",
    "can_send_order": false,
    "display_title": "RGNT range breakout conditionnel",
    "display_message": "Pas d'entree immediate. Attendre une cloture 15m au-dessus de 4.55 puis trigger STP_LMT a 4.57 avec trailing stop attache.",
    "next_action": "WAIT_15M_CLOSE_ABOVE_4_55_AND_PREPARE_ATTACHED_TRAILING_STOP",
    "blocking_reasons": [
      "current_price_below_trigger",
      "trailing_stop_order_ready_false",
      "broker_stop_not_confirmed"
    ],
    "warnings": [
      "micro_cap_high_volatility",
      "warrant_overhang_near_4_20",
      "private_placement_support_near_3_50",
      "paper_mode_recommended"
    ],
    "planned_vs_current_risk": {
      "worst_fill_price": 4.62,
      "initial_trailing_stop": 4.06,
      "risk_per_share_usd": 0.56,
      "maximum_quantity": 26,
      "planned_max_risk_usd": 14.56
    }
  },
  "targets": [],
  "notes": "Setup choisi: range_breakout. RGNT a rejete la zone haute intraday proche de 4.50 et reste tres speculatif. Pas d'achat sous 4.57. Le vrai signal est une cloture 15m au-dessus de 4.55 avec volume valide. Stop initial trailing calcule a 4.06, sous la zone 4.20 pour eviter un stop trop serre sur simple retest. Si le prix depasse 4.62 sans fill, ne pas chasser: attendre retest 4.42-4.55. Si retour sous 3.50, setup invalide."
}
